pulpcore/__init__.py
pulpcore/client/__init__.py
pulpcore/client/pulp_ostree/__init__.py
pulpcore/client/pulp_ostree/api_client.py
pulpcore/client/pulp_ostree/api_response.py
pulpcore/client/pulp_ostree/configuration.py
pulpcore/client/pulp_ostree/exceptions.py
pulpcore/client/pulp_ostree/py.typed
pulpcore/client/pulp_ostree/rest.py
pulpcore/client/pulp_ostree/api/__init__.py
pulpcore/client/pulp_ostree/api/content_commits_api.py
pulpcore/client/pulp_ostree/api/content_configs_api.py
pulpcore/client/pulp_ostree/api/content_content_api.py
pulpcore/client/pulp_ostree/api/content_objects_api.py
pulpcore/client/pulp_ostree/api/content_refs_api.py
pulpcore/client/pulp_ostree/api/content_summaries_api.py
pulpcore/client/pulp_ostree/api/distributions_ostree_api.py
pulpcore/client/pulp_ostree/api/remotes_ostree_api.py
pulpcore/client/pulp_ostree/api/repositories_ostree_api.py
pulpcore/client/pulp_ostree/api/repositories_ostree_versions_api.py
pulpcore/client/pulp_ostree/models/__init__.py
pulpcore/client/pulp_ostree/models/async_operation_response.py
pulpcore/client/pulp_ostree/models/content_summary_response.py
pulpcore/client/pulp_ostree/models/my_permissions_response.py
pulpcore/client/pulp_ostree/models/nested_role.py
pulpcore/client/pulp_ostree/models/nested_role_response.py
pulpcore/client/pulp_ostree/models/object_roles_response.py
pulpcore/client/pulp_ostree/models/ostree_import_all.py
pulpcore/client/pulp_ostree/models/ostree_import_commits_to_ref.py
pulpcore/client/pulp_ostree/models/ostree_ostree_commit_response.py
pulpcore/client/pulp_ostree/models/ostree_ostree_config_response.py
pulpcore/client/pulp_ostree/models/ostree_ostree_content.py
pulpcore/client/pulp_ostree/models/ostree_ostree_content_response.py
pulpcore/client/pulp_ostree/models/ostree_ostree_distribution.py
pulpcore/client/pulp_ostree/models/ostree_ostree_distribution_response.py
pulpcore/client/pulp_ostree/models/ostree_ostree_object_response.py
pulp_ostree_client-2.6.0.dist-info/METADATA
pulp_ostree_client-2.6.0.dist-info/WHEEL
pulp_ostree_client-2.6.0.dist-info/top_level.txt
pulp_ostree_client-2.6.0.dist-info/RECORD
